<?xml version="1.0" encoding="UTF-8"?><stops line="41" iti="1">﻿<stop><id>4076</id><name>HEROS</name><present>TRUE</present><latitude>50.803</latitude><longitude>4.342</longitude></stop><stop><id>1943</id><name>STATUAIRES</name><latitude></latitude><longitude></longitude></stop><stop><id>1968</id><name>ZEECRABBE</name><latitude></latitude><longitude></longitude></stop><stop><id>1969</id><name>HOUZEAU</name><latitude></latitude><longitude></longitude></stop><stop><id>1970</id><name>FLORIDE</name><latitude></latitude><longitude></longitude></stop><stop><id>2714</id><name>HOPITAL SAINTE-ELISABETH</name><latitude></latitude><longitude></longitude></stop><stop><id>2715</id><name>VERT CHASSEUR</name><present>TRUE</present><latitude></latitude><longitude></longitude></stop><stop><id>6440</id><name>MONTANA</name><latitude></latitude><longitude></longitude></stop><stop><id>2721</id><name>GENDARMES</name><latitude></latitude><longitude></longitude></stop><stop><id>5415</id><name>BRESIL</name><present>TRUE</present><latitude></latitude><longitude></longitude></stop><stop><id>5416</id><name>BOONDAEL GARE</name><latitude></latitude><longitude></longitude></stop><stop><id>2074</id><name>FUTAIE</name><latitude></latitude><longitude></longitude></stop><stop><id>2076</id><name>DRIES</name><latitude></latitude><longitude></longitude></stop><stop><id>2115</id><name>BIEN-FAIRE</name><latitude></latitude><longitude></longitude></stop><stop><id>2080</id><name>WATERMAEL GARE</name><present>TRUE</present><latitude></latitude><longitude></longitude></stop><stop><id>4310</id><name>KEYM</name><latitude></latitude><longitude></longitude></stop><stop><id>4401</id><name>LOUTRIER</name><latitude></latitude><longitude></longitude></stop><stop><id>4402</id><name>HANNETONS</name><latitude></latitude><longitude></longitude></stop><stop><id>4403</id><name>ARCHIDUCS</name><latitude></latitude><longitude></longitude></stop><stop><id>4408</id><name>TRITOMAS</name><latitude></latitude><longitude></longitude></stop><stop><id>4405</id><name>PECHERIES</name><latitude></latitude><longitude></longitude></stop><stop><id>3549</id><name>VIGNETTE</name><latitude></latitude><longitude></longitude></stop><stop><id>6469</id><name>DEMEY</name><latitude></latitude><longitude></longitude></stop><stop><id>2046</id><name>HERRMANN-DEBROUX</name><present>TRUE</present><latitude></latitude><longitude></longitude></stop><stop><id>1723</id><name>SCHOONEJANS</name><present>TRUE</present><latitude></latitude><longitude></longitude></stop><stop><id>1724</id><name>SACRE-COEUR</name><latitude></latitude><longitude></longitude></stop></stops>