<?xml version="1.0" encoding="UTF-8"?><stops line="59" iti="1">﻿<stop><id>3125</id><name>HOPITAL ETT.-IXELLES</name><present>TRUE</present><latitude>50.825</latitude><longitude>4.38</longitude></stop><stop><id>6158</id><name>LEVURE</name><latitude></latitude><longitude></longitude></stop><stop><id>1280</id><name>FLAGEY</name><latitude></latitude><longitude></longitude></stop><stop><id>3155</id><name>WERY</name><latitude></latitude><longitude></longitude></stop><stop><id>3156</id><name>NATATION</name><latitude></latitude><longitude></longitude></stop><stop><id>3160</id><name>ETANGS</name><present>TRUE</present><latitude></latitude><longitude></longitude></stop><stop><id>3158</id><name>JOURDAN</name><latitude></latitude><longitude></longitude></stop><stop><id>3159</id><name>PARC LEOPOLD</name><latitude></latitude><longitude></longitude></stop><stop><id>6464</id><name>MAELBEEK</name><latitude></latitude><longitude></longitude></stop><stop><id>2970</id><name>LIVINGSTONE</name><latitude></latitude><longitude></longitude></stop><stop><id>1569</id><name>GUTENBERG</name><latitude></latitude><longitude></longitude></stop><stop><id>1582</id><name>SAINT-JOSSE</name><latitude></latitude><longitude></longitude></stop><stop><id>3162</id><name>HOUWAERT</name><latitude></latitude><longitude></longitude></stop><stop><id>3163</id><name>GEEFS</name><present>TRUE</present><latitude></latitude><longitude></longitude></stop><stop><id>3164</id><name>COTEAUX</name><latitude></latitude><longitude></longitude></stop><stop><id>3165</id><name>HERMAN</name><latitude></latitude><longitude></longitude></stop><stop><id>3166</id><name>ERNEST LAUDE</name><latitude></latitude><longitude></longitude></stop><stop><id>3167</id><name>EENENS</name><latitude></latitude><longitude></longitude></stop><stop><id>3168</id><name>VERBOEKHOVEN</name><latitude></latitude><longitude></longitude></stop><stop><id>6459</id><name>PRINCESSE ELISABETH</name><present>TRUE</present><latitude></latitude><longitude></longitude></stop><stop><id>3177</id><name>SCHAERBEEK GARE</name><latitude></latitude><longitude></longitude></stop><stop><id>3180</id><name>HUART- HAMOIR</name><latitude></latitude><longitude></longitude></stop><stop><id>3181</id><name>ANATOLE FRANCE</name><latitude></latitude><longitude></longitude></stop><stop><id>3172</id><name>CHAUMONTEL</name><latitude></latitude><longitude></longitude></stop><stop><id>3173</id><name>CARLI</name><latitude></latitude><longitude></longitude></stop><stop><id>3174</id><name>PICARDIE</name><latitude></latitude><longitude></longitude></stop><stop><id>3175</id><name>SAINT-VINCENT</name><present>TRUE</present><latitude></latitude><longitude></longitude></stop><stop><id>3176</id><name>VANDENHOVEN</name><latitude></latitude><longitude></longitude></stop><stop><id>5299</id><name>BORDET STATION</name><latitude></latitude><longitude></longitude></stop></stops>